cli/__init__.py
cli/main.py
core/__init__.py
core/dataset_delta.py
core/delta.py
core/delta_rust.py
core/delta_streaming.py
core/differential_compress.py
core/fast_reconstruct.py
core/lazy_loading.py
core/mmap_storage.py
core/model_cache.py
core/parallel_compress.py
core/smart_heuristics.py
sparse_core/__init__.py
sparse_core/sparse_core.abi3.so
sparse_llm-0.0.5.dist-info/METADATA
sparse_llm-0.0.5.dist-info/WHEEL
sparse_llm-0.0.5.dist-info/entry_points.txt
sparse_llm-0.0.5.dist-info/licenses/LICENSE
sparse_llm-0.0.5.dist-info/RECORD
