Metadata-Version: 2.4
Name: sparse-llm
Version: 0.0.5
Classifier: Development Status :: 4 - Beta
Classifier: Intended Audience :: Developers
Classifier: Intended Audience :: Science/Research
Classifier: Programming Language :: Python :: 3
Classifier: Programming Language :: Python :: 3.9
Classifier: Programming Language :: Python :: 3.10
Classifier: Programming Language :: Python :: 3.11
Classifier: Programming Language :: Rust
Classifier: Topic :: Scientific/Engineering :: Artificial Intelligence
Requires-Dist: torch>=2.0.0
Requires-Dist: transformers>=4.30.0
Requires-Dist: datasets>=2.14.0
Requires-Dist: tqdm>=4.65.0
Requires-Dist: numpy>=1.21.0
Requires-Dist: safetensors>=0.3.0
Requires-Dist: pytest>=7.0.0 ; extra == 'dev'
Requires-Dist: black>=23.0.0 ; extra == 'dev'
Requires-Dist: ruff>=0.0.280 ; extra == 'dev'
Provides-Extra: dev
License-File: LICENSE
Summary: Delta compression for LLM fine-tunes - lossless or LoRA-equivalent SVD compression
Keywords: llm,delta-compression,model-optimization,fine-tuning,lora,svd
Author-email: Gagan Suie <singhga029@gmail.com>
License: Apache-2.0
Requires-Python: >=3.9
Project-URL: Homepage, https://github.com/gagansuie/sparse
Project-URL: Documentation, https://github.com/gagansuie/sparse#readme
Project-URL: Repository, https://github.com/gagansuie/sparse
